hamichlol/__init__.py
hamichlol/exceptions.py
hamichlol/hamichlol.py
hamichlol/util.py
hamichlol-1.4.0.dist-info/LICENSE
hamichlol-1.4.0.dist-info/METADATA
hamichlol-1.4.0.dist-info/WHEEL
hamichlol-1.4.0.dist-info/top_level.txt
hamichlol-1.4.0.dist-info/RECORD
